{
    "$schema": "http://json-schema.org/draft-04/schema#",
    "id" : "http://schema.humancellatlas.org/module/ontology/4.0.0/species_ontology.json",
    "description": "A term that may be associated with a cell type-related ontology term",
    "additionalProperties": false,
        "required": [
        "text"
    ],
    "title": "species_ontology",
    "properties": {
        "$schema" : {
            "pattern" : "http://schema.humancellatlas.org/module/ontology/[0-9]{1,}.[0-9]{1,}.[0-9]{1,}/species_ontology.json",
            "type": "string"
        },
        "text": {
            "description": "The name of the species to which the organism belongs.",
            "type": "string"
        },
        "ontology": {
            "description": "An ontology term identifier in the form prefix:accession",
            "type": "string",
            "graph_restriction":  {
                "ontologies" : ["obo:NCBITaxon"],
                "classes": ["NCBITaxon:131567"],
                "relations": ["rdfs:subClassOf"],
                "direct": false,
                "include_self": false
            }
        }
    },
    "type": "object"
}