{       
    "$schema": "http://json-schema.org/draft-04/schema#", 
    "description":    "", 
    "properties": {
        "sample_type": {
            "type": "string",
            "enum": ["cell suspension"]
         },
        "cell_type": {
            "description" : "cell types present in suspension",
            "type": "array",
            "items": {"$ref": "cell_type_ontology.json" }
       },
        "disassociation_protocol": {
            "description": "How body part was treated to disassociate it into cells that can float individually in solution in sorter or microfluidics device.", 
            "pattern": "^P-....-.*$", 
            "type": "string"
        }, 
        "enrichment": {
            "description": "How cells were enriched for specific type or to weed out common types after disassociation.",
            "type": "array",            
            "items": { "$ref": "enrichment.json" }
        },
        "total_estimated_cells": {
            "description": "Total estimated number of cells in sample.  May be 1 for well based assays.",
            "maximum": 1000000000.0,
            "minimum": 0.1,
            "type": "number"
        },
        "well": {
            "$ref": "well.json",
            "description": "If sample was isolated in a well in plate (or fluidics chip), information about that"
        }
     }
}